{
  "message":"Go Serverless v1.0! Your function executed successfully!",
  "input":{
    "resource":"/reset",
    "path":"/reset",
    "httpMethod":"POST",
    "headers":{
      "Accept":"application/json,*/*",
      "Accept-Encoding":"gzip,deflate",
      "CloudFront-Forwarded-Proto":"https",
      "CloudFront-Is-Desktop-Viewer":"true",
      "CloudFront-Is-Mobile-Viewer":"false",
      "CloudFront-Is-SmartTV-Viewer":"false",
      "CloudFront-Is-Tablet-Viewer":"false",
      "CloudFront-Viewer-Country":"US",
      "Content-Type":"application/x-www-form-urlencoded",
      "Host":"z0o543kfqd.execute-api.eu-central-1.amazonaws.com",
      "User-Agent":"Slackbot 1.0 (+https://api.slack.com/robots)",
      "Via":"1.1 e223f938e1f7716ebc7a1a8faefd0900.cloudfront.net (CloudFront)",
      "X-Amz-Cf-Id":"ABCs9ANuGSSUCrnQ3McLsZYKNLb144yyAwrgMc_uLIOnAY3KZJpwaQ==",
      "X-Amzn-Trace-Id":"Root=1-59ac476e-6559c8d5575e40f7486fbe8e",
      "X-Forwarded-For":"54.165.241.61, 54.182.230.11",
      "X-Forwarded-Port":"443",
      "X-Forwarded-Proto":"https"
    },
    "queryStringParameters":null,
    "pathParameters":null,
    "stageVariables":null,
    "requestContext":{
      "path":"/dev/reset",
      "accountId":"845404844455",
      "resourceId":"92apw3",
      "stage":"dev",
      "requestId":"455b0a26-90d4-11e7-ad51-13b4c3f7daf9",
      "identity":{
        "cognitoIdentityPoolId":null,
        "accountId":null,
        "cognitoIdentityId":null,
        "caller":null,
        "apiKey":"",
        "sourceIp":"54.165.241.61",
        "accessKey":null,
        "cognitoAuthenticationType":null,
        "cognitoAuthenticationProvider":null,
        "userArn":null,
        "userAgent":"Slackbot 1.0 (+https://api.slack.com/robots)",
        "user":null
      },
      "resourcePath":"/reset",
      "httpMethod":"POST",
      "apiId":"z0o543kfqd"
    },
    "body":"token=CYlFjb3d6SGunrnvttnRsaV2&team_id=T0EJTUQ87&team_domain=hackyourfuture&channel_id=D3Y3D1GQK&channel_name=directmessage&user_id=U3Y5DFFK4&user_name=rob&command=%2Fdbreset&text=&response_url=https%3A%2F%2Fhooks.slack.com%2Fcommands%2FT0EJTUQ87%2F235126032673%2F9R0Tq2njZEbditUqAZCODyd7&trigger_id=235006157488.14639976279.b3416eb7d47b04c3c7caf4b7105ee65d",
    "isBase64Encoded":false
  }
}